{
  "data": [
    {
      "id": 1,
      "name": "شیراز",
      "image": "/assets/foodCategory/website_image_irani_1.jpg",
      "headerImage": "",
      "score": "",
      "category": "ایرانی،اش و حلیم",
      "express": false,
      "deliveryPrice": "۳۵،۰۰۰ تومان"
    },
    {
        "id": 2,
        "name": "برگر هیزمی",
        "image": "/assets/foodCategory/website_image_irani_1.jpg",
        "headerImage": "",
        "score": "۱",
        "category": "فست فود، پیتزا ایتالیایی",
        "express": false,
        "deliveryPrice": "۳۵،۰۰۰ تومان"
      },
      {
        "id": 3,
        "name": "رستوران اعیان",
        "image": "/assets/foodCategory/website_image_irani_1.jpg",
        "headerImage": "",
        "score": "3",
        "category": "ایرانی، چلو خورشت، چلو کباب",
        "express": false,
        "deliveryPrice": "۳۵،۰۰۰ تومان"
      },
      {
        "id": 4,
        "name": "غذای سالم فوپک",
        "image": "/assets/foodCategory/website_image_irani_1.jpg",
        "headerImage": "",
        "score": "۴۰",
        "category": "ساندویچ، فست فود، سالاد",
        "express": false,
        "deliveryPrice": "۳۵،۰۰۰ تومان"
      }
  ]
}
